{
  "src/index.js": {
    "bundled": 7710,
    "minified": 7028,
    "gzipped": 1479
  },
  "src/ButtonTab/ButtonTab.js": {
    "bundled": 1803,
    "minified": 1243,
    "gzipped": 623
  },
  "src/DataTable/DataTable.js": {
    "bundled": 9941,
    "minified": 5272,
    "gzipped": 1795
  },
  "src/ClosableDialogTitle/ClosableDialogTitle.js": {
    "bundled": 2661,
    "minified": 1803,
    "gzipped": 697
  },
  "src/DateField/DateField.js": {
    "bundled": 8737,
    "minified": 4785,
    "gzipped": 1708
  },
  "src/NavTabs/NavTabs.js": {
    "bundled": 2460,
    "minified": 1618,
    "gzipped": 790
  },
  "src/NavTab/NavTab.js": {
    "bundled": 1248,
    "minified": 903,
    "gzipped": 504
  },
  "src/ThemeProvider/ThemeContext.js": {
    "bundled": 720,
    "minified": 553,
    "gzipped": 314
  },
  "src/ThemeProvider/ThemeProvider.js": {
    "bundled": 2772,
    "minified": 1692,
    "gzipped": 655
  },
  "src/ThemeProvider/useTheme.js": {
    "bundled": 971,
    "minified": 701,
    "gzipped": 387
  },
  "src/Spacer/Spacer.js": {
    "bundled": 1456,
    "minified": 929,
    "gzipped": 499
  },
  "src/CircleLoader/CircleLoader.js": {
    "bundled": 2239,
    "minified": 1661,
    "gzipped": 731
  },
  "src/ColorPicker/ColorPicker.js": {
    "bundled": 6370,
    "minified": 3667,
    "gzipped": 1217
  },
  "src/CurrencyField/CurrencyField.js": {
    "bundled": 3656,
    "minified": 2359,
    "gzipped": 805
  },
  "src/ConfirmationDialog/ConfirmationDialog.js": {
    "bundled": 2932,
    "minified": 2036,
    "gzipped": 663
  },
  "src/DeviceProvider/DeviceProvider.js": {
    "bundled": 3057,
    "minified": 1681,
    "gzipped": 745
  },
  "src/LoaderProvider/LoaderProvider.js": {
    "bundled": 3288,
    "minified": 2226,
    "gzipped": 769
  },
  "src/Dropzone/Dropzone.js": {
    "bundled": 10473,
    "minified": 5789,
    "gzipped": 2117
  },
  "src/GoogleMapsProvider/GoogleMapsProvider.js": {
    "bundled": 2935,
    "minified": 1979,
    "gzipped": 853
  },
  "src/GoogleMapsProvider/GoogleMapsContext.js": {
    "bundled": 740,
    "minified": 573,
    "gzipped": 318
  },
  "src/GoogleMapsProvider/useGoogleMaps.js": {
    "bundled": 1031,
    "minified": 756,
    "gzipped": 396
  },
  "src/LoaderProvider/useLoader.js": {
    "bundled": 982,
    "minified": 711,
    "gzipped": 388
  },
  "src/GoogleMapsProvider/usePlacesAutocomplete.js": {
    "bundled": 1769,
    "minified": 1090,
    "gzipped": 534
  },
  "src/GoogleMapsProvider/useGeocoder.js": {
    "bundled": 1628,
    "minified": 1002,
    "gzipped": 510
  },
  "src/MenuPanelLoader/MenuPanelLoader.js": {
    "bundled": 1020,
    "minified": 776,
    "gzipped": 422
  },
  "src/MenuPanelItem/MenuPanelItem.js": {
    "bundled": 7458,
    "minified": 4359,
    "gzipped": 1462
  },
  "src/MenuPanelTitle/MenuPanelTitle.js": {
    "bundled": 2192,
    "minified": 1489,
    "gzipped": 567
  },
  "src/MiniLoader/MiniLoader.js": {
    "bundled": 3232,
    "minified": 1966,
    "gzipped": 867
  },
  "src/PasswordField/PasswordField.js": {
    "bundled": 9765,
    "minified": 6199,
    "gzipped": 1830
  },
  "src/SearchLocationsField/SearchLocationsField.js": {
    "bundled": 7470,
    "minified": 4292,
    "gzipped": 1406
  },
  "src/SnackbarProvider/SnackbarContext.js": {
    "bundled": 732,
    "minified": 565,
    "gzipped": 315
  },
  "src/SnackbarProvider/useSnackbar.js": {
    "bundled": 1005,
    "minified": 732,
    "gzipped": 390
  },
  "src/SaveButtonsDialog/SaveButtonsDialog.js": {
    "bundled": 2674,
    "minified": 1810,
    "gzipped": 798
  },
  "src/TextEditor/TextEditor.js": {
    "bundled": 4152,
    "minified": 2352,
    "gzipped": 901
  },
  "src/useDebounce/useDebounce.js": {
    "bundled": 2268,
    "minified": 897,
    "gzipped": 472
  },
  "src/useDimensions/useDimensions.js": {
    "bundled": 3174,
    "minified": 1384,
    "gzipped": 630
  },
  "src/useValues/useValues.js": {
    "bundled": 2420,
    "minified": 1492,
    "gzipped": 595
  },
  "src/utils/functional.js": {
    "bundled": 436,
    "minified": 307,
    "gzipped": 223
  },
  "src/useSelectionSet/useSelectionSet.js": {
    "bundled": 2326,
    "minified": 1203,
    "gzipped": 580
  },
  "src/utils/arrays.js": {
    "bundled": 302,
    "minified": 277,
    "gzipped": 198
  },
  "src/ButtonTabs/ButtonTabs.js": {
    "bundled": 2392,
    "minified": 1679,
    "gzipped": 807
  },
  "src/utils/text.js": {
    "bundled": 2243,
    "minified": 789,
    "gzipped": 452
  },
  "src/LoaderProvider/LoaderContext.js": {
    "bundled": 724,
    "minified": 557,
    "gzipped": 314
  },
  "src/styles/theme.js": {
    "bundled": 14464,
    "minified": 6926,
    "gzipped": 1942
  },
  "src/utils/files.js": {
    "bundled": 1639,
    "minified": 842,
    "gzipped": 512
  },
  "src/icons/ArrowLeftCircleIcon.js": {
    "bundled": 893,
    "minified": 716,
    "gzipped": 364
  },
  "src/styles/colors.js": {
    "bundled": 4282,
    "minified": 3508,
    "gzipped": 773
  },
  "src/icons/ArrowRightCircleIcon.js": {
    "bundled": 898,
    "minified": 720,
    "gzipped": 365
  },
  "src/icons/ArrowUpCircleIcon.js": {
    "bundled": 883,
    "minified": 708,
    "gzipped": 362
  },
  "src/icons/FacebookIcon.js": {
    "bundled": 996,
    "minified": 826,
    "gzipped": 443
  },
  "src/icons/GoogleIcon.js": {
    "bundled": 996,
    "minified": 828,
    "gzipped": 443
  },
  "src/icons/InstagramIcon.js": {
    "bundled": 1181,
    "minified": 1010,
    "gzipped": 479
  },
  "src/icons/TwitterIcon.js": {
    "bundled": 1348,
    "minified": 1179,
    "gzipped": 610
  },
  "src/utils/math.js": {
    "bundled": 329,
    "minified": 216,
    "gzipped": 163
  },
  "src/icons/FileAudioIcon.js": {
    "bundled": 901,
    "minified": 730,
    "gzipped": 401
  },
  "src/icons/FileExcelIcon.js": {
    "bundled": 922,
    "minified": 751,
    "gzipped": 411
  },
  "src/icons/FilePowerpointIcon.js": {
    "bundled": 941,
    "minified": 765,
    "gzipped": 400
  },
  "src/icons/LinkedInIcon.js": {
    "bundled": 1115,
    "minified": 945,
    "gzipped": 486
  },
  "src/icons/FilePDFIcon.js": {
    "bundled": 1950,
    "minified": 1781,
    "gzipped": 887
  },
  "src/icons/FileWordIcon.js": {
    "bundled": 906,
    "minified": 736,
    "gzipped": 400
  },
  "src/icons/ArrowDownCircleIcon.js": {
    "bundled": 893,
    "minified": 716,
    "gzipped": 363
  },
  "src/Shell/withShell.js": {
    "bundled": 1029,
    "minified": 660,
    "gzipped": 347
  },
  "src/Shell/useShell.js": {
    "bundled": 1356,
    "minified": 771,
    "gzipped": 413
  },
  "src/Shell/ShellContext.js": {
    "bundled": 720,
    "minified": 553,
    "gzipped": 314
  },
  "src/Shell/Shell.js": {
    "bundled": 3909,
    "minified": 2273,
    "gzipped": 940
  },
  "_virtual/_rollupPluginBabelHelpers.js": {
    "bundled": 10251,
    "minified": 6815,
    "gzipped": 2098
  },
  "src/DataTable/useResizableColumns.js": {
    "bundled": 3569,
    "minified": 1681,
    "gzipped": 790
  },
  "src/DataTable/context.js": {
    "bundled": 809,
    "minified": 620,
    "gzipped": 330
  },
  "src/DataTable/styles.js": {
    "bundled": 6676,
    "minified": 4147,
    "gzipped": 1258
  },
  "src/utils/geo.js": {
    "bundled": 2173,
    "minified": 1218,
    "gzipped": 667
  },
  "src/SnackbarProvider/SnackbarMessage.js": {
    "bundled": 584,
    "minified": 282,
    "gzipped": 186
  },
  "src/TextEditor/context.js": {
    "bundled": 849,
    "minified": 655,
    "gzipped": 335
  },
  "src/TextEditor/Element.js": {
    "bundled": 2335,
    "minified": 1519,
    "gzipped": 615
  },
  "src/TextEditor/ButtonPanel.js": {
    "bundled": 6669,
    "minified": 4659,
    "gzipped": 1369
  },
  "src/TextEditor/Input.js": {
    "bundled": 2511,
    "minified": 1608,
    "gzipped": 730
  },
  "src/TextEditor/styles.js": {
    "bundled": 2605,
    "minified": 1819,
    "gzipped": 783
  },
  "src/TextEditor/utils.js": {
    "bundled": 4291,
    "minified": 2510,
    "gzipped": 903
  },
  "src/TextEditor/Leaf.js": {
    "bundled": 1352,
    "minified": 882,
    "gzipped": 451
  },
  "src/DataTable/components/HeaderCell.js": {
    "bundled": 7521,
    "minified": 4440,
    "gzipped": 1487
  },
  "src/DataTable/components/TotalCell.js": {
    "bundled": 2685,
    "minified": 1788,
    "gzipped": 708
  },
  "src/DataTable/components/DataCell.js": {
    "bundled": 6006,
    "minified": 3459,
    "gzipped": 1163
  },
  "src/DataTable/components/ResultsLoader.js": {
    "bundled": 630,
    "minified": 512,
    "gzipped": 295
  },
  "src/TextEditor/plugins/links.js": {
    "bundled": 2922,
    "minified": 743,
    "gzipped": 401
  },
  "src/Shell/components/AppBar.js": {
    "bundled": 2449,
    "minified": 1597,
    "gzipped": 777
  },
  "src/Shell/components/UserMenu.js": {
    "bundled": 3427,
    "minified": 2280,
    "gzipped": 910
  },
  "src/Shell/components/MenuPanel.js": {
    "bundled": 5042,
    "minified": 3051,
    "gzipped": 1134
  },
  "node_modules/prop-types/index.js": {
    "bundled": 1063,
    "minified": 493,
    "gzipped": 264
  },
  "node_modules/react-fast-compare/index.js": {
    "bundled": 4482,
    "minified": 1758,
    "gzipped": 675
  },
  "node_modules/clsx/dist/clsx.m.js": {
    "bundled": 688,
    "minified": 392,
    "gzipped": 243
  },
  "node_modules/react-window/dist/index.esm.js": {
    "bundled": 42539,
    "minified": 16510,
    "gzipped": 4818
  },
  "node_modules/react-number-format/dist/react-number-format.es.js": {
    "bundled": 49202,
    "minified": 18349,
    "gzipped": 6087
  },
  "node_modules/zxcvbn/lib/main.js": {
    "bundled": 1429,
    "minified": 849,
    "gzipped": 447
  },
  "node_modules/slate-history/dist/index.es.js": {
    "bundled": 5644,
    "minified": 2399,
    "gzipped": 918
  },
  "node_modules/slate-react/dist/index.es.js": {
    "bundled": 86824,
    "minified": 38094,
    "gzipped": 10471
  },
  "src/TextEditor/LinkDialog.js": {
    "bundled": 4519,
    "minified": 3002,
    "gzipped": 1015
  },
  "src/TextEditor/ActionButton.js": {
    "bundled": 1915,
    "minified": 1201,
    "gzipped": 576
  },
  "node_modules/slate/dist/index.es.js": {
    "bundled": 145522,
    "minified": 60334,
    "gzipped": 14957
  },
  "_virtual/_commonjsHelpers.js": {
    "bundled": 254,
    "minified": 202,
    "gzipped": 149
  },
  "src/icons/SortAlphaDescendingIcon.js": {
    "bundled": 883,
    "minified": 706,
    "gzipped": 391
  },
  "src/icons/SortAlphaIcon.js": {
    "bundled": 996,
    "minified": 825,
    "gzipped": 454
  },
  "src/icons/SortAlphaAscendingIcon.js": {
    "bundled": 900,
    "minified": 720,
    "gzipped": 390
  },
  "src/SnackbarProvider/SnackbarProvider.js": {
    "bundled": 608,
    "minified": 367,
    "gzipped": 256
  },
  "src/icons/SortNumberDescendingIcon.js": {
    "bundled": 1001,
    "minified": 823,
    "gzipped": 430
  },
  "src/icons/SortGenericAscendingIcon.js": {
    "bundled": 819,
    "minified": 641,
    "gzipped": 343
  },
  "src/icons/SortGenericDescendingIcon.js": {
    "bundled": 817,
    "minified": 639,
    "gzipped": 343
  },
  "src/icons/SortNumberIcon.js": {
    "bundled": 2071,
    "minified": 1899,
    "gzipped": 924
  },
  "src/icons/SortGenericIcon.js": {
    "bundled": 805,
    "minified": 632,
    "gzipped": 342
  },
  "src/DataTable/components/SortableHeader.js": {
    "bundled": 1335,
    "minified": 856,
    "gzipped": 458
  },
  "_virtual/factoryWithThrowingShims.js_commonjs-proxy": {
    "bundled": 158,
    "minified": 148,
    "gzipped": 116
  },
  "node_modules/@emotion/cache/dist/cache.esm.js": {
    "bundled": 8224,
    "minified": 3218,
    "gzipped": 1459
  },
  "_virtual/factoryWithTypeCheckers.js_commonjs-proxy": {
    "bundled": 155,
    "minified": 145,
    "gzipped": 117
  },
  "node_modules/prop-types/factoryWithThrowingShims.js": {
    "bundled": 1679,
    "minified": 865,
    "gzipped": 452
  },
  "node_modules/prop-types/factoryWithTypeCheckers.js": {
    "bundled": 21663,
    "minified": 7024,
    "gzipped": 2281
  },
  "node_modules/is-url/index.js": {
    "bundled": 894,
    "minified": 377,
    "gzipped": 246
  },
  "node_modules/ngeohash/main.js": {
    "bundled": 15318,
    "minified": 4010,
    "gzipped": 1497
  },
  "node_modules/is-hotkey/lib/index.js": {
    "bundled": 4336,
    "minified": 2145,
    "gzipped": 1160
  },
  "_virtual/feedback.js_commonjs-proxy": {
    "bundled": 110,
    "minified": 100,
    "gzipped": 101
  },
  "_virtual/scoring.js_commonjs-proxy": {
    "bundled": 107,
    "minified": 97,
    "gzipped": 99
  },
  "node_modules/zxcvbn/lib/feedback.js": {
    "bundled": 4226,
    "minified": 2691,
    "gzipped": 1134
  },
  "_virtual/matching.js_commonjs-proxy": {
    "bundled": 110,
    "minified": 100,
    "gzipped": 101
  },
  "node_modules/zxcvbn/lib/scoring.js": {
    "bundled": 14341,
    "minified": 6517,
    "gzipped": 2481
  },
  "node_modules/zxcvbn/lib/time_estimates.js": {
    "bundled": 2206,
    "minified": 975,
    "gzipped": 469
  },
  "_virtual/time_estimates.js_commonjs-proxy": {
    "bundled": 128,
    "minified": 118,
    "gzipped": 106
  },
  "node_modules/zxcvbn/lib/matching.js": {
    "bundled": 21767,
    "minified": 8794,
    "gzipped": 3660
  },
  "node_modules/react-draggable/build/cjs/cjs.js": {
    "bundled": 724,
    "minified": 380,
    "gzipped": 187
  },
  "node_modules/dom-helpers/esm/scrollbarSize.js": {
    "bundled": 627,
    "minified": 407,
    "gzipped": 270
  },
  "node_modules/lodash/isEqual.js": {
    "bundled": 1033,
    "minified": 153,
    "gzipped": 126
  },
  "node_modules/file-selector/dist/es5/file-selector.js": {
    "bundled": 6998,
    "minified": 2828,
    "gzipped": 999
  },
  "node_modules/lodash/throttle.js": {
    "bundled": 2759,
    "minified": 404,
    "gzipped": 257
  },
  "node_modules/lodash/omit.js": {
    "bundled": 1705,
    "minified": 746,
    "gzipped": 359
  },
  "node_modules/@babel/runtime/helpers/esm/inheritsLoose.js": {
    "bundled": 297,
    "minified": 207,
    "gzipped": 149
  },
  "node_modules/@babel/runtime/helpers/esm/objectWithoutPropertiesLoose.js": {
    "bundled": 399,
    "minified": 220,
    "gzipped": 178
  },
  "node_modules/@babel/runtime/helpers/esm/assertThisInitialized.js": {
    "bundled": 234,
    "minified": 195,
    "gzipped": 155
  },
  "node_modules/@babel/runtime/helpers/esm/extends.js": {
    "bundled": 425,
    "minified": 258,
    "gzipped": 196
  },
  "node_modules/prop-types/checkPropTypes.js": {
    "bundled": 3880,
    "minified": 1490,
    "gzipped": 714
  },
  "_virtual/checkPropTypes.js_commonjs-proxy": {
    "bundled": 128,
    "minified": 118,
    "gzipped": 106
  },
  "_virtual/index.js_commonjs-proxy": {
    "bundled": 123,
    "minified": 113,
    "gzipped": 106
  },
  "node_modules/prop-types/node_modules/react-is/index.js": {
    "bundled": 487,
    "minified": 406,
    "gzipped": 218
  },
  "node_modules/slate-react/node_modules/is-plain-object/index.es.js": {
    "bundled": 1089,
    "minified": 712,
    "gzipped": 350
  },
  "node_modules/slate-history/node_modules/is-plain-object/index.es.js": {
    "bundled": 1089,
    "minified": 712,
    "gzipped": 350
  },
  "_virtual/ReactPropTypesSecret.js_commonjs-proxy": {
    "bundled": 150,
    "minified": 140,
    "gzipped": 112
  },
  "node_modules/prop-types/lib/ReactPropTypesSecret.js": {
    "bundled": 367,
    "minified": 167,
    "gzipped": 131
  },
  "node_modules/slate/node_modules/is-plain-object/index.es.js": {
    "bundled": 1089,
    "minified": 712,
    "gzipped": 350
  },
  "node_modules/memoize-one/dist/memoize-one.esm.js": {
    "bundled": 981,
    "minified": 381,
    "gzipped": 248
  },
  "_virtual/adjacency_graphs.js_commonjs-proxy": {
    "bundled": 134,
    "minified": 124,
    "gzipped": 107
  },
  "node_modules/slate/node_modules/immer/dist/immer.esm.js": {
    "bundled": 10368,
    "minified": 10274,
    "gzipped": 4047
  },
  "_virtual/frequency_lists.js_commonjs-proxy": {
    "bundled": 131,
    "minified": 121,
    "gzipped": 106
  },
  "node_modules/zxcvbn/lib/adjacency_graphs.js": {
    "bundled": 10775,
    "minified": 7906,
    "gzipped": 1777
  },
  "node_modules/dom-helpers/esm/canUseDOM.js": {
    "bundled": 146,
    "minified": 132,
    "gzipped": 122
  },
  "node_modules/esrever/esrever.js": {
    "bundled": 2482,
    "minified": 918,
    "gzipped": 543
  },
  "node_modules/direction/index.js": {
    "bundled": 561,
    "minified": 291,
    "gzipped": 281
  },
  "_virtual/Draggable.js_commonjs-proxy": {
    "bundled": 140,
    "minified": 130,
    "gzipped": 113
  },
  "node_modules/scroll-into-view-if-needed/es/index.js": {
    "bundled": 1455,
    "minified": 807,
    "gzipped": 436
  },
  "node_modules/tiny-invariant/dist/tiny-invariant.esm.js": {
    "bundled": 333,
    "minified": 215,
    "gzipped": 169
  },
  "node_modules/react-draggable/build/cjs/Draggable.js": {
    "bundled": 22851,
    "minified": 9831,
    "gzipped": 3339
  },
  "node_modules/file-selector/dist/es5/file.js": {
    "bundled": 2015,
    "minified": 1044,
    "gzipped": 523
  },
  "node_modules/@emotion/sheet/dist/sheet.esm.js": {
    "bundled": 4160,
    "minified": 1406,
    "gzipped": 680
  },
  "node_modules/@emotion/stylis/dist/stylis.esm.js": {
    "bundled": 15960,
    "minified": 8247,
    "gzipped": 3213
  },
  "node_modules/@emotion/weak-memoize/dist/weak-memoize.esm.js": {
    "bundled": 388,
    "minified": 166,
    "gzipped": 138
  },
  "node_modules/lodash/_baseIsEqual.js": {
    "bundled": 1075,
    "minified": 318,
    "gzipped": 185
  },
  "_virtual/_baseIsEqual.js_commonjs-proxy": {
    "bundled": 118,
    "minified": 108,
    "gzipped": 102
  },
  "node_modules/lodash/isObject.js": {
    "bundled": 777,
    "minified": 144,
    "gzipped": 127
  },
  "_virtual/debounce.js_commonjs-proxy": {
    "bundled": 106,
    "minified": 96,
    "gzipped": 96
  },
  "node_modules/lodash/debounce.js": {
    "bundled": 6153,
    "minified": 1154,
    "gzipped": 580
  },
  "_virtual/isObject.js_commonjs-proxy": {
    "bundled": 106,
    "minified": 96,
    "gzipped": 98
  },
  "src/icons/SortNumberAscendingIcon.js": {
    "bundled": 1006,
    "minified": 829,
    "gzipped": 429
  },
  "node_modules/lodash/_arrayMap.js": {
    "bundled": 598,
    "minified": 162,
    "gzipped": 148
  },
  "node_modules/lodash/_castPath.js": {
    "bundled": 627,
    "minified": 291,
    "gzipped": 176
  },
  "_virtual/_baseClone.js_commonjs-proxy": {
    "bundled": 112,
    "minified": 102,
    "gzipped": 99
  },
  "_virtual/_castPath.js_commonjs-proxy": {
    "bundled": 109,
    "minified": 99,
    "gzipped": 99
  },
  "_virtual/_arrayMap.js_commonjs-proxy": {
    "bundled": 109,
    "minified": 99,
    "gzipped": 100
  },
  "node_modules/lodash/_copyObject.js": {
    "bundled": 1100,
    "minified": 360,
    "gzipped": 233
  },
  "node_modules/lodash/_customOmitClone.js": {
    "bundled": 534,
    "minified": 191,
    "gzipped": 139
  },
  "_virtual/_copyObject.js_commonjs-proxy": {
    "bundled": 115,
    "minified": 105,
    "gzipped": 102
  },
  "node_modules/lodash/_flatRest.js": {
    "bundled": 512,
    "minified": 250,
    "gzipped": 159
  },
  "_virtual/_flatRest.js_commonjs-proxy": {
    "bundled": 109,
    "minified": 99,
    "gzipped": 99
  },
  "_virtual/_customOmitClone.js_commonjs-proxy": {
    "bundled": 130,
    "minified": 120,
    "gzipped": 105
  },
  "node_modules/lodash/_getAllKeysIn.js": {
    "bundled": 551,
    "minified": 271,
    "gzipped": 160
  },
  "node_modules/lodash/_baseClone.js": {
    "bundled": 5749,
    "minified": 3292,
    "gzipped": 1030
  },
  "_virtual/_getAllKeysIn.js_commonjs-proxy": {
    "bundled": 121,
    "minified": 111,
    "gzipped": 105
  },
  "_virtual/_baseUnset.js_commonjs-proxy": {
    "bundled": 112,
    "minified": 102,
    "gzipped": 99
  },
  "node_modules/lodash/_baseUnset.js": {
    "bundled": 642,
    "minified": 290,
    "gzipped": 183
  },
  "node_modules/tslib/tslib.es6.js": {
    "bundled": 4026,
    "minified": 2746,
    "gzipped": 1381
  },
  "node_modules/prop-types/node_modules/react-is/cjs/react-is.development.js": {
    "bundled": 7182,
    "minified": 2877,
    "gzipped": 1127
  },
  "node_modules/prop-types/node_modules/react-is/cjs/react-is.production.min.js": {
    "bundled": 4233,
    "minified": 3917,
    "gzipped": 1216
  },
  "_virtual/react-is.production.min.js_commonjs-proxy": {
    "bundled": 190,
    "minified": 177,
    "gzipped": 135
  },
  "_virtual/react-is.development.js_commonjs-proxy": {
    "bundled": 170,
    "minified": 160,
    "gzipped": 126
  },
  "node_modules/@babel/runtime/helpers/esm/setPrototypeOf.js": {
    "bundled": 235,
    "minified": 164,
    "gzipped": 124
  },
  "node_modules/object-assign/index.js": {
    "bundled": 2141,
    "minified": 1170,
    "gzipped": 593
  },
  "_virtual/index2.js_commonjs-proxy": {
    "bundled": 104,
    "minified": 94,
    "gzipped": 99
  },
  "node_modules/lodash/_baseIsEqualDeep.js": {
    "bundled": 3103,
    "minified": 1182,
    "gzipped": 498
  },
  "_virtual/_baseIsEqualDeep.js_commonjs-proxy": {
    "bundled": 130,
    "minified": 120,
    "gzipped": 105
  },
  "_virtual/isObjectLike.js_commonjs-proxy": {
    "bundled": 118,
    "minified": 108,
    "gzipped": 103
  },
  "node_modules/lodash/isObjectLike.js": {
    "bundled": 666,
    "minified": 135,
    "gzipped": 119
  },
  "_virtual/now.js_commonjs-proxy": {
    "bundled": 91,
    "minified": 81,
    "gzipped": 93
  },
  "_virtual/toNumber.js_commonjs-proxy": {
    "bundled": 106,
    "minified": 96,
    "gzipped": 98
  },
  "node_modules/lodash/now.js": {
    "bundled": 559,
    "minified": 116,
    "gzipped": 120
  },
  "_virtual/_arrayEach.js_commonjs-proxy": {
    "bundled": 112,
    "minified": 102,
    "gzipped": 100
  },
  "node_modules/lodash/_arrayEach.js": {
    "bundled": 581,
    "minified": 157,
    "gzipped": 144
  },
  "_virtual/_baseAssign.js_commonjs-proxy": {
    "bundled": 115,
    "minified": 105,
    "gzipped": 100
  },
  "node_modules/lodash/_Stack.js": {
    "bundled": 800,
    "minified": 517,
    "gzipped": 228
  },
  "node_modules/lodash/_baseAssign.js": {
    "bundled": 524,
    "minified": 197,
    "gzipped": 143
  },
  "_virtual/_Stack.js_commonjs-proxy": {
    "bundled": 100,
    "minified": 90,
    "gzipped": 96
  },
  "_virtual/_baseAssignIn.js_commonjs-proxy": {
    "bundled": 121,
    "minified": 111,
    "gzipped": 103
  },
  "node_modules/lodash/_copyArray.js": {
    "bundled": 498,
    "minified": 154,
    "gzipped": 137
  },
  "node_modules/lodash/_baseAssignIn.js": {
    "bundled": 540,
    "minified": 211,
    "gzipped": 151
  },
  "node_modules/lodash/_cloneBuffer.js": {
    "bundled": 1232,
    "minified": 427,
    "gzipped": 269
  },
  "_virtual/_copyArray.js_commonjs-proxy": {
    "bundled": 112,
    "minified": 102,
    "gzipped": 100
  },
  "node_modules/lodash/toNumber.js": {
    "bundled": 1574,
    "minified": 610,
    "gzipped": 346
  },
  "node_modules/lodash/_copySymbolsIn.js": {
    "bundled": 532,
    "minified": 233,
    "gzipped": 149
  },
  "_virtual/_cloneBuffer.js_commonjs-proxy": {
    "bundled": 118,
    "minified": 108,
    "gzipped": 101
  },
  "_virtual/_copySymbolsIn.js_commonjs-proxy": {
    "bundled": 124,
    "minified": 114,
    "gzipped": 105
  },
  "node_modules/lodash/_copySymbols.js": {
    "bundled": 504,
    "minified": 219,
    "gzipped": 146
  },
  "_virtual/_copySymbols.js_commonjs-proxy": {
    "bundled": 118,
    "minified": 108,
    "gzipped": 102
  },
  "node_modules/lodash/_getAllKeys.js": {
    "bundled": 514,
    "minified": 251,
    "gzipped": 153
  },
  "_virtual/_getAllKeys.js_commonjs-proxy": {
    "bundled": 115,
    "minified": 105,
    "gzipped": 102
  },
  "_virtual/_getTag.js_commonjs-proxy": {
    "bundled": 103,
    "minified": 93,
    "gzipped": 97
  },
  "node_modules/lodash/_assignValue.js": {
    "bundled": 955,
    "minified": 337,
    "gzipped": 208
  },
  "node_modules/lodash/_getTag.js": {
    "bundled": 1927,
    "minified": 1191,
    "gzipped": 455
  },
  "_virtual/_assignValue.js_commonjs-proxy": {
    "bundled": 118,
    "minified": 108,
    "gzipped": 101
  },
  "node_modules/lodash/_initCloneByTag.js": {
    "bundled": 2340,
    "minified": 1431,
    "gzipped": 487
  },
  "_virtual/_initCloneByTag.js_commonjs-proxy": {
    "bundled": 127,
    "minified": 117,
    "gzipped": 106
  },
  "node_modules/lodash/isArray.js": {
    "bundled": 530,
    "minified": 82,
    "gzipped": 75
  },
  "_virtual/_initCloneObject.js_commonjs-proxy": {
    "bundled": 130,
    "minified": 120,
    "gzipped": 106
  },
  "_virtual/isArray.js_commonjs-proxy": {
    "bundled": 103,
    "minified": 93,
    "gzipped": 97
  },
  "node_modules/lodash/_initCloneObject.js": {
    "bundled": 557,
    "minified": 329,
    "gzipped": 183
  },
  "_virtual/isBuffer.js_commonjs-proxy": {
    "bundled": 106,
    "minified": 96,
    "gzipped": 98
  },
  "node_modules/lodash/isMap.js": {
    "bundled": 667,
    "minified": 252,
    "gzipped": 147
  },
  "node_modules/lodash/isBuffer.js": {
    "bundled": 1289,
    "minified": 370,
    "gzipped": 230
  },
  "_virtual/isMap.js_commonjs-proxy": {
    "bundled": 97,
    "minified": 87,
    "gzipped": 96
  },
  "_virtual/isSet.js_commonjs-proxy": {
    "bundled": 97,
    "minified": 87,
    "gzipped": 96
  },
  "_virtual/keys.js_commonjs-proxy": {
    "bundled": 94,
    "minified": 84,
    "gzipped": 94
  },
  "node_modules/lodash/keys.js": {
    "bundled": 933,
    "minified": 247,
    "gzipped": 157
  },
  "node_modules/lodash/keysIn.js": {
    "bundled": 831,
    "minified": 264,
    "gzipped": 163
  },
  "node_modules/lodash/isSet.js": {
    "bundled": 667,
    "minified": 252,
    "gzipped": 147
  },
  "_virtual/keysIn.js_commonjs-proxy": {
    "bundled": 100,
    "minified": 90,
    "gzipped": 97
  },
  "_virtual/_initCloneArray.js_commonjs-proxy": {
    "bundled": 127,
    "minified": 117,
    "gzipped": 104
  },
  "node_modules/lodash/_isKey.js": {
    "bundled": 922,
    "minified": 410,
    "gzipped": 280
  },
  "node_modules/lodash/_initCloneArray.js": {
    "bundled": 746,
    "minified": 320,
    "gzipped": 211
  },
  "_virtual/_isKey.js_commonjs-proxy": {
    "bundled": 100,
    "minified": 90,
    "gzipped": 97
  },
  "node_modules/lodash/toString.js": {
    "bundled": 629,
    "minified": 167,
    "gzipped": 133
  },
  "_virtual/toString.js_commonjs-proxy": {
    "bundled": 106,
    "minified": 96,
    "gzipped": 98
  },
  "_virtual/_stringToPath.js_commonjs-proxy": {
    "bundled": 121,
    "minified": 111,
    "gzipped": 103
  },
  "node_modules/lodash/_stringToPath.js": {
    "bundled": 895,
    "minified": 435,
    "gzipped": 292
  },
  "node_modules/lodash/_baseAssignValue.js": {
    "bundled": 687,
    "minified": 278,
    "gzipped": 183
  },
  "_virtual/_baseAssignValue.js_commonjs-proxy": {
    "bundled": 130,
    "minified": 120,
    "gzipped": 105
  },
  "node_modules/lodash/isPlainObject.js": {
    "bundled": 1717,
    "minified": 678,
    "gzipped": 322
  },
  "_virtual/isPlainObject.js_commonjs-proxy": {
    "bundled": 121,
    "minified": 111,
    "gzipped": 103
  },
  "_virtual/_overRest.js_commonjs-proxy": {
    "bundled": 109,
    "minified": 99,
    "gzipped": 99
  },
  "_virtual/_setToString.js_commonjs-proxy": {
    "bundled": 118,
    "minified": 108,
    "gzipped": 102
  },
  "node_modules/lodash/_overRest.js": {
    "bundled": 1143,
    "minified": 355,
    "gzipped": 246
  },
  "node_modules/lodash/_setToString.js": {
    "bundled": 450,
    "minified": 196,
    "gzipped": 119
  },
  "_virtual/flatten.js_commonjs-proxy": {
    "bundled": 103,
    "minified": 93,
    "gzipped": 95
  },
  "node_modules/lodash/_getSymbolsIn.js": {
    "bundled": 822,
    "minified": 403,
    "gzipped": 213
  },
  "_virtual/_getSymbolsIn.js_commonjs-proxy": {
    "bundled": 121,
    "minified": 111,
    "gzipped": 104
  },
  "node_modules/lodash/flatten.js": {
    "bundled": 536,
    "minified": 174,
    "gzipped": 144
  },
  "_virtual/_baseGetAllKeys.js_commonjs-proxy": {
    "bundled": 127,
    "minified": 117,
    "gzipped": 106
  },
  "node_modules/lodash/_baseGetAllKeys.js": {
    "bundled": 801,
    "minified": 234,
    "gzipped": 161
  },
  "node_modules/lodash/last.js": {
    "bundled": 437,
    "minified": 116,
    "gzipped": 122
  },
  "_virtual/last.js_commonjs-proxy": {
    "bundled": 94,
    "minified": 84,
    "gzipped": 93
  },
  "node_modules/lodash/_toKey.js": {
    "bundled": 562,
    "minified": 212,
    "gzipped": 178
  },
  "_virtual/_toKey.js_commonjs-proxy": {
    "bundled": 100,
    "minified": 90,
    "gzipped": 96
  },
  "_virtual/_parent.js_commonjs-proxy": {
    "bundled": 103,
    "minified": 93,
    "gzipped": 95
  },
  "node_modules/lodash/_parent.js": {
    "bundled": 484,
    "minified": 203,
    "gzipped": 156
  },
  "node_modules/react-draggable/build/cjs/DraggableCore.js": {
    "bundled": 23947,
    "minified": 9145,
    "gzipped": 3067
  },
  "_virtual/DraggableCore.js_commonjs-proxy": {
    "bundled": 156,
    "minified": 146,
    "gzipped": 119
  },
  "node_modules/react-draggable/build/cjs/utils/shims.js": {
    "bundled": 1495,
    "minified": 919,
    "gzipped": 453
  },
  "_virtual/domFns.js_commonjs-proxy": {
    "bundled": 136,
    "minified": 123,
    "gzipped": 118
  },
  "_virtual/shims.js_commonjs-proxy": {
    "bundled": 133,
    "minified": 120,
    "gzipped": 116
  },
  "node_modules/react-draggable/build/cjs/utils/domFns.js": {
    "bundled": 12955,
    "minified": 7551,
    "gzipped": 2219
  },
  "_virtual/positionFns.js_commonjs-proxy": {
    "bundled": 151,
    "minified": 138,
    "gzipped": 124
  },
  "node_modules/react-draggable/build/cjs/utils/positionFns.js": {
    "bundled": 6218,
    "minified": 3212,
    "gzipped": 1121
  },
  "_virtual/log.js_commonjs-proxy": {
    "bundled": 122,
    "minified": 112,
    "gzipped": 116
  },
  "node_modules/react-draggable/build/cjs/utils/log.js": {
    "bundled": 296,
    "minified": 222,
    "gzipped": 151
  },
  "_virtual/index3.js_commonjs-proxy": {
    "bundled": 101,
    "minified": 91,
    "gzipped": 98
  },
  "_virtual/index4.js_commonjs-proxy": {
    "bundled": 101,
    "minified": 91,
    "gzipped": 98
  },
  "node_modules/classnames/index.js": {
    "bundled": 1250,
    "minified": 752,
    "gzipped": 468
  },
  "node_modules/compute-scroll-into-view/dist/index.module.js": {
    "bundled": 2516,
    "minified": 2502,
    "gzipped": 1213
  },
  "node_modules/lodash/_equalByTag.js": {
    "bundled": 3822,
    "minified": 1489,
    "gzipped": 630
  },
  "_virtual/_equalByTag.js_commonjs-proxy": {
    "bundled": 115,
    "minified": 105,
    "gzipped": 101
  },
  "node_modules/lodash/_equalObjects.js": {
    "bundled": 3027,
    "minified": 878,
    "gzipped": 486
  },
  "_virtual/_equalObjects.js_commonjs-proxy": {
    "bundled": 121,
    "minified": 111,
    "gzipped": 103
  },
  "_virtual/_equalArrays.js_commonjs-proxy": {
    "bundled": 118,
    "minified": 108,
    "gzipped": 102
  },
  "node_modules/lodash/_equalArrays.js": {
    "bundled": 2725,
    "minified": 782,
    "gzipped": 448
  },
  "_virtual/isTypedArray.js_commonjs-proxy": {
    "bundled": 118,
    "minified": 108,
    "gzipped": 103
  },
  "node_modules/lodash/isTypedArray.js": {
    "bundled": 763,
    "minified": 329,
    "gzipped": 155
  },
  "_virtual/_root.js_commonjs-proxy": {
    "bundled": 97,
    "minified": 87,
    "gzipped": 94
  },
  "node_modules/lodash/_stackClear.js": {
    "bundled": 305,
    "minified": 172,
    "gzipped": 138
  },
  "node_modules/lodash/_root.js": {
    "bundled": 339,
    "minified": 208,
    "gzipped": 162
  },
  "_virtual/_stackClear.js_commonjs-proxy": {
    "bundled": 115,
    "minified": 105,
    "gzipped": 100
  },
  "node_modules/lodash/_ListCache.js": {
    "bundled": 938,
    "minified": 607,
    "gzipped": 257
  },
  "node_modules/lodash/_stackGet.js": {
    "bundled": 313,
    "minified": 110,
    "gzipped": 105
  },
  "_virtual/_ListCache.js_commonjs-proxy": {
    "bundled": 112,
    "minified": 102,
    "gzipped": 101
  },
  "_virtual/_stackGet.js_commonjs-proxy": {
    "bundled": 109,
    "minified": 99,
    "gzipped": 99
  },
  "_virtual/_stackHas.js_commonjs-proxy": {
    "bundled": 109,
    "minified": 99,
    "gzipped": 99
  },
  "node_modules/lodash/_stackHas.js": {
    "bundled": 365,
    "minified": 110,
    "gzipped": 105
  },
  "node_modules/lodash/_stackSet.js": {
    "bundled": 910,
    "minified": 430,
    "gzipped": 254
  },
  "_virtual/_stackDelete.js_commonjs-proxy": {
    "bundled": 118,
    "minified": 108,
    "gzipped": 101
  },
  "node_modules/lodash/_stackDelete.js": {
    "bundled": 453,
    "minified": 154,
    "gzipped": 127
  },
  "_virtual/_stackSet.js_commonjs-proxy": {
    "bundled": 109,
    "minified": 99,
    "gzipped": 99
  },
  "_virtual/_baseTrim.js_commonjs-proxy": {
    "bundled": 109,
    "minified": 99,
    "gzipped": 99
  },
  "node_modules/lodash/_baseTrim.js": {
    "bundled": 491,
    "minified": 223,
    "gzipped": 167
  },
  "_virtual/isSymbol.js_commonjs-proxy": {
    "bundled": 106,
    "minified": 96,
    "gzipped": 99
  },
  "node_modules/lodash/isSymbol.js": {
    "bundled": 734,
    "minified": 267,
    "gzipped": 179
  },
  "node_modules/lodash/_getSymbols.js": {
    "bundled": 940,
    "minified": 444,
    "gzipped": 238
  },
  "_virtual/_getSymbols.js_commonjs-proxy": {
    "bundled": 115,
    "minified": 105,
    "gzipped": 102
  },
  "node_modules/lodash/eq.js": {
    "bundled": 831,
    "minified": 87,
    "gzipped": 100
  },
  "_virtual/eq.js_commonjs-proxy": {
    "bundled": 88,
    "minified": 78,
    "gzipped": 92
  },
  "_virtual/_Map.js_commonjs-proxy": {
    "bundled": 94,
    "minified": 84,
    "gzipped": 95
  },
  "node_modules/lodash/_Map.js": {
    "bundled": 237,
    "minified": 140,
    "gzipped": 114
  },
  "_virtual/_DataView.js_commonjs-proxy": {
    "bundled": 109,
    "minified": 99,
    "gzipped": 100
  },
  "node_modules/lodash/_DataView.js": {
    "bundled": 262,
    "minified": 165,
    "gzipped": 120
  },
  "node_modules/lodash/_Promise.js": {
    "bundled": 261,
    "minified": 164,
    "gzipped": 120
  },
  "_virtual/_Promise.js_commonjs-proxy": {
    "bundled": 106,
    "minified": 96,
    "gzipped": 98
  },
  "node_modules/lodash/_Set.js": {
    "bundled": 237,
    "minified": 140,
    "gzipped": 114
  },
  "_virtual/_Set.js_commonjs-proxy": {
    "bundled": 94,
    "minified": 84,
    "gzipped": 95
  },
  "_virtual/_WeakMap.js_commonjs-proxy": {
    "bundled": 106,
    "minified": 96,
    "gzipped": 99
  },
  "node_modules/lodash/_WeakMap.js": {
    "bundled": 257,
    "minified": 160,
    "gzipped": 119
  },
  "_virtual/_baseGetTag.js_commonjs-proxy": {
    "bundled": 115,
    "minified": 105,
    "gzipped": 102
  },
  "node_modules/lodash/_baseGetTag.js": {
    "bundled": 854,
    "minified": 444,
    "gzipped": 234
  },
  "_virtual/_toSource.js_commonjs-proxy": {
    "bundled": 109,
    "minified": 99,
    "gzipped": 99
  },
  "node_modules/lodash/_toSource.js": {
    "bundled": 598,
    "minified": 237,
    "gzipped": 163
  },
  "_virtual/_cloneDataView.js_commonjs-proxy": {
    "bundled": 124,
    "minified": 114,
    "gzipped": 104
  },
  "_virtual/_cloneArrayBuffer.js_commonjs-proxy": {
    "bundled": 133,
    "minified": 123,
    "gzipped": 105
  },
  "node_modules/lodash/_cloneDataView.js": {
    "bundled": 564,
    "minified": 259,
    "gzipped": 171
  },
  "_virtual/_cloneSymbol.js_commonjs-proxy": {
    "bundled": 118,
    "minified": 108,
    "gzipped": 102
  },
  "node_modules/lodash/_cloneArrayBuffer.js": {
    "bundled": 513,
    "minified": 248,
    "gzipped": 164
  },
  "_virtual/_cloneTypedArray.js_commonjs-proxy": {
    "bundled": 130,
    "minified": 120,
    "gzipped": 105
  },
  "_virtual/_cloneRegExp.js_commonjs-proxy": {
    "bundled": 118,
    "minified": 108,
    "gzipped": 103
  },
  "_virtual/_getPrototype.js_commonjs-proxy": {
    "bundled": 121,
    "minified": 111,
    "gzipped": 102
  },
  "node_modules/lodash/_cloneRegExp.js": {
    "bundled": 487,
    "minified": 196,
    "gzipped": 155
  },
  "_virtual/_baseCreate.js_commonjs-proxy": {
    "bundled": 115,
    "minified": 105,
    "gzipped": 100
  },
  "node_modules/lodash/_baseCreate.js": {
    "bundled": 735,
    "minified": 305,
    "gzipped": 185
  },
  "node_modules/lodash/_getPrototype.js": {
    "bundled": 218,
    "minified": 159,
    "gzipped": 119
  },
  "_virtual/_isPrototype.js_commonjs-proxy": {
    "bundled": 118,
    "minified": 108,
    "gzipped": 102
  },
  "node_modules/lodash/_isPrototype.js": {
    "bundled": 528,
    "minified": 210,
    "gzipped": 148
  },
  "node_modules/lodash/_cloneTypedArray.js": {
    "bundled": 588,
    "minified": 263,
    "gzipped": 173
  },
  "_virtual/_baseUnary.js_commonjs-proxy": {
    "bundled": 112,
    "minified": 102,
    "gzipped": 100
  },
  "node_modules/lodash/_baseUnary.js": {
    "bundled": 376,
    "minified": 118,
    "gzipped": 101
  },
  "node_modules/lodash/_cloneSymbol.js": {
    "bundled": 578,
    "minified": 282,
    "gzipped": 177
  },
  "node_modules/lodash/_baseIsMap.js": {
    "bundled": 530,
    "minified": 229,
    "gzipped": 163
  },
  "_virtual/_baseIsMap.js_commonjs-proxy": {
    "bundled": 112,
    "minified": 102,
    "gzipped": 101
  },
  "_virtual/_nodeUtil.js_commonjs-proxy": {
    "bundled": 109,
    "minified": 99,
    "gzipped": 98
  },
  "node_modules/lodash/stubFalse.js": {
    "bundled": 326,
    "minified": 96,
    "gzipped": 90
  },
  "node_modules/lodash/_nodeUtil.js": {
    "bundled": 1165,
    "minified": 427,
    "gzipped": 256
  },
  "_virtual/stubFalse.js_commonjs-proxy": {
    "bundled": 109,
    "minified": 99,
    "gzipped": 99
  },
  "_virtual/_arrayLikeKeys.js_commonjs-proxy": {
    "bundled": 124,
    "minified": 114,
    "gzipped": 104
  },
  "node_modules/lodash/_arrayLikeKeys.js": {
    "bundled": 1852,
    "minified": 729,
    "gzipped": 366
  },
  "_virtual/_baseKeys.js_commonjs-proxy": {
    "bundled": 109,
    "minified": 99,
    "gzipped": 100
  },
  "node_modules/lodash/_baseKeys.js": {
    "bundled": 828,
    "minified": 376,
    "gzipped": 227
  },
  "_virtual/isArrayLike.js_commonjs-proxy": {
    "bundled": 115,
    "minified": 105,
    "gzipped": 102
  },
  "node_modules/lodash/isArrayLike.js": {
    "bundled": 886,
    "minified": 223,
    "gzipped": 157
  },
  "node_modules/lodash/_baseKeysIn.js": {
    "bundled": 929,
    "minified": 436,
    "gzipped": 244
  },
  "_virtual/_baseKeysIn.js_commonjs-proxy": {
    "bundled": 115,
    "minified": 105,
    "gzipped": 102
  },
  "_virtual/_baseIsSet.js_commonjs-proxy": {
    "bundled": 112,
    "minified": 102,
    "gzipped": 101
  },
  "node_modules/lodash/_baseIsSet.js": {
    "bundled": 530,
    "minified": 229,
    "gzipped": 161
  },
  "_virtual/_baseToString.js_commonjs-proxy": {
    "bundled": 121,
    "minified": 111,
    "gzipped": 103
  },
  "_virtual/_memoizeCapped.js_commonjs-proxy": {
    "bundled": 124,
    "minified": 114,
    "gzipped": 103
  },
  "node_modules/lodash/_baseToString.js": {
    "bundled": 1221,
    "minified": 540,
    "gzipped": 277
  },
  "_virtual/_defineProperty.js_commonjs-proxy": {
    "bundled": 127,
    "minified": 117,
    "gzipped": 104
  },
  "node_modules/lodash/_memoizeCapped.js": {
    "bundled": 688,
    "minified": 256,
    "gzipped": 182
  },
  "node_modules/lodash/_defineProperty.js": {
    "bundled": 292,
    "minified": 224,
    "gzipped": 158
  },
  "node_modules/lodash/_apply.js": {
    "bundled": 750,
    "minified": 237,
    "gzipped": 156
  },
  "_virtual/_apply.js_commonjs-proxy": {
    "bundled": 100,
    "minified": 90,
    "gzipped": 95
  },
  "node_modules/lodash/_baseSetToString.js": {
    "bundled": 709,
    "minified": 353,
    "gzipped": 196
  },
  "_virtual/_baseSetToString.js_commonjs-proxy": {
    "bundled": 130,
    "minified": 120,
    "gzipped": 106
  },
  "node_modules/lodash/_shortOut.js": {
    "bundled": 983,
    "minified": 289,
    "gzipped": 217
  },
  "_virtual/_shortOut.js_commonjs-proxy": {
    "bundled": 109,
    "minified": 99,
    "gzipped": 99
  },
  "_virtual/_arrayPush.js_commonjs-proxy": {
    "bundled": 112,
    "minified": 102,
    "gzipped": 100
  },
  "node_modules/lodash/_arrayPush.js": {
    "bundled": 481,
    "minified": 151,
    "gzipped": 134
  },
  "node_modules/lodash/stubArray.js": {
    "bundled": 436,
    "minified": 96,
    "gzipped": 90
  },
  "_virtual/stubArray.js_commonjs-proxy": {
    "bundled": 109,
    "minified": 99,
    "gzipped": 99
  },
  "node_modules/lodash/_baseFlatten.js": {
    "bundled": 1259,
    "minified": 348,
    "gzipped": 224
  },
  "_virtual/_baseFlatten.js_commonjs-proxy": {
    "bundled": 118,
    "minified": 108,
    "gzipped": 101
  },
  "node_modules/lodash/_baseGet.js": {
    "bundled": 666,
    "minified": 248,
    "gzipped": 190
  },
  "_virtual/_baseGet.js_commonjs-proxy": {
    "bundled": 106,
    "minified": 96,
    "gzipped": 98
  },
  "node_modules/lodash/_baseSlice.js": {
    "bundled": 800,
    "minified": 222,
    "gzipped": 185
  },
  "_virtual/_baseSlice.js_commonjs-proxy": {
    "bundled": 112,
    "minified": 102,
    "gzipped": 100
  },
  "_virtual/getPrefix.js_commonjs-proxy": {
    "bundled": 146,
    "minified": 136,
    "gzipped": 122
  },
  "node_modules/react-draggable/build/cjs/utils/getPrefix.js": {
    "bundled": 2216,
    "minified": 936,
    "gzipped": 487
  },
  "_virtual/_Symbol.js_commonjs-proxy": {
    "bundled": 103,
    "minified": 93,
    "gzipped": 98
  },
  "node_modules/lodash/_Symbol.js": {
    "bundled": 161,
    "minified": 103,
    "gzipped": 97
  },
  "node_modules/lodash/_Uint8Array.js": {
    "bundled": 181,
    "minified": 123,
    "gzipped": 101
  },
  "_virtual/_Uint8Array.js_commonjs-proxy": {
    "bundled": 115,
    "minified": 105,
    "gzipped": 103
  },
  "node_modules/lodash/_mapToArray.js": {
    "bundled": 409,
    "minified": 165,
    "gzipped": 143
  },
  "node_modules/lodash/_setToArray.js": {
    "bundled": 391,
    "minified": 159,
    "gzipped": 137
  },
  "_virtual/_mapToArray.js_commonjs-proxy": {
    "bundled": 115,
    "minified": 105,
    "gzipped": 102
  },
  "_virtual/_setToArray.js_commonjs-proxy": {
    "bundled": 115,
    "minified": 105,
    "gzipped": 102
  },
  "node_modules/lodash/_SetCache.js": {
    "bundled": 689,
    "minified": 386,
    "gzipped": 221
  },
  "_virtual/_SetCache.js_commonjs-proxy": {
    "bundled": 109,
    "minified": 99,
    "gzipped": 100
  },
  "node_modules/lodash/_arraySome.js": {
    "bundled": 638,
    "minified": 162,
    "gzipped": 144
  },
  "_virtual/_arraySome.js_commonjs-proxy": {
    "bundled": 112,
    "minified": 102,
    "gzipped": 100
  },
  "node_modules/lodash/_cacheHas.js": {
    "bundled": 379,
    "minified": 100,
    "gzipped": 99
  },
  "_virtual/_cacheHas.js_commonjs-proxy": {
    "bundled": 109,
    "minified": 99,
    "gzipped": 99
  },
  "node_modules/lodash/_baseIsTypedArray.js": {
    "bundled": 2291,
    "minified": 1673,
    "gzipped": 506
  },
  "_virtual/_baseIsTypedArray.js_commonjs-proxy": {
    "bundled": 133,
    "minified": 123,
    "gzipped": 106
  },
  "_virtual/_freeGlobal.js_commonjs-proxy": {
    "bundled": 115,
    "minified": 105,
    "gzipped": 100
  },
  "node_modules/lodash/_freeGlobal.js": {
    "bundled": 219,
    "minified": 142,
    "gzipped": 106
  },
  "node_modules/lodash/_listCacheClear.js": {
    "bundled": 272,
    "minified": 134,
    "gzipped": 112
  },
  "node_modules/lodash/_listCacheDelete.js": {
    "bundled": 836,
    "minified": 323,
    "gzipped": 224
  },
  "_virtual/_listCacheClear.js_commonjs-proxy": {
    "bundled": 127,
    "minified": 117,
    "gzipped": 103
  },
  "_virtual/_listCacheDelete.js_commonjs-proxy": {
    "bundled": 130,
    "minified": 120,
    "gzipped": 104
  },
  "node_modules/lodash/_listCacheGet.js": {
    "bundled": 475,
    "minified": 213,
    "gzipped": 164
  },
  "_virtual/_listCacheGet.js_commonjs-proxy": {
    "bundled": 121,
    "minified": 111,
    "gzipped": 103
  },
  "node_modules/lodash/_listCacheSet.js": {
    "bundled": 608,
    "minified": 243,
    "gzipped": 182
  },
  "_virtual/_listCacheSet.js_commonjs-proxy": {
    "bundled": 121,
    "minified": 111,
    "gzipped": 103
  },
  "node_modules/lodash/_listCacheHas.js": {
    "bundled": 458,
    "minified": 187,
    "gzipped": 143
  },
  "_virtual/_listCacheHas.js_commonjs-proxy": {
    "bundled": 121,
    "minified": 111,
    "gzipped": 103
  },
  "node_modules/lodash/_MapCache.js": {
    "bundled": 936,
    "minified": 583,
    "gzipped": 257
  },
  "_virtual/_MapCache.js_commonjs-proxy": {
    "bundled": 109,
    "minified": 99,
    "gzipped": 100
  },
  "_virtual/_trimmedEndIndex.js_commonjs-proxy": {
    "bundled": 130,
    "minified": 120,
    "gzipped": 106
  },
  "node_modules/lodash/_trimmedEndIndex.js": {
    "bundled": 571,
    "minified": 198,
    "gzipped": 152
  },
  "node_modules/lodash/_arrayFilter.js": {
    "bundled": 680,
    "minified": 188,
    "gzipped": 158
  },
  "_virtual/_arrayFilter.js_commonjs-proxy": {
    "bundled": 118,
    "minified": 108,
    "gzipped": 101
  },
  "node_modules/lodash/_getNative.js": {
    "bundled": 537,
    "minified": 226,
    "gzipped": 154
  },
  "_virtual/_getNative.js_commonjs-proxy": {
    "bundled": 112,
    "minified": 102,
    "gzipped": 100
  },
  "node_modules/lodash/_getRawTag.js": {
    "bundled": 1189,
    "minified": 493,
    "gzipped": 259
  },
  "_virtual/_getRawTag.js_commonjs-proxy": {
    "bundled": 112,
    "minified": 102,
    "gzipped": 101
  },
  "_virtual/_objectToString.js_commonjs-proxy": {
    "bundled": 127,
    "minified": 117,
    "gzipped": 104
  },
  "node_modules/lodash/_objectToString.js": {
    "bundled": 619,
    "minified": 217,
    "gzipped": 143
  },
  "_virtual/_overArg.js_commonjs-proxy": {
    "bundled": 106,
    "minified": 96,
    "gzipped": 98
  },
  "node_modules/lodash/_overArg.js": {
    "bundled": 422,
    "minified": 115,
    "gzipped": 104
  },
  "node_modules/lodash/_nativeKeys.js": {
    "bundled": 255,
    "minified": 141,
    "gzipped": 116
  },
  "_virtual/_nativeKeys.js_commonjs-proxy": {
    "bundled": 115,
    "minified": 105,
    "gzipped": 101
  },
  "node_modules/lodash/isArguments.js": {
    "bundled": 1085,
    "minified": 476,
    "gzipped": 230
  },
  "_virtual/isArguments.js_commonjs-proxy": {
    "bundled": 115,
    "minified": 105,
    "gzipped": 102
  },
  "_virtual/_baseTimes.js_commonjs-proxy": {
    "bundled": 112,
    "minified": 102,
    "gzipped": 99
  },
  "node_modules/lodash/_baseTimes.js": {
    "bundled": 548,
    "minified": 138,
    "gzipped": 129
  },
  "node_modules/lodash/_isIndex.js": {
    "bundled": 799,
    "minified": 265,
    "gzipped": 231
  },
  "_virtual/_isIndex.js_commonjs-proxy": {
    "bundled": 106,
    "minified": 96,
    "gzipped": 98
  },
  "node_modules/lodash/isLength.js": {
    "bundled": 846,
    "minified": 182,
    "gzipped": 163
  },
  "_virtual/isLength.js_commonjs-proxy": {
    "bundled": 106,
    "minified": 96,
    "gzipped": 98
  },
  "node_modules/lodash/isFunction.js": {
    "bundled": 1049,
    "minified": 395,
    "gzipped": 215
  },
  "_virtual/isFunction.js_commonjs-proxy": {
    "bundled": 112,
    "minified": 102,
    "gzipped": 99
  },
  "node_modules/lodash/_nativeKeysIn.js": {
    "bundled": 540,
    "minified": 160,
    "gzipped": 138
  },
  "_virtual/_nativeKeysIn.js_commonjs-proxy": {
    "bundled": 121,
    "minified": 111,
    "gzipped": 104
  },
  "node_modules/lodash/memoize.js": {
    "bundled": 2272,
    "minified": 473,
    "gzipped": 293
  },
  "_virtual/memoize.js_commonjs-proxy": {
    "bundled": 103,
    "minified": 93,
    "gzipped": 96
  },
  "node_modules/lodash/constant.js": {
    "bundled": 572,
    "minified": 112,
    "gzipped": 97
  },
  "_virtual/constant.js_commonjs-proxy": {
    "bundled": 106,
    "minified": 96,
    "gzipped": 96
  },
  "node_modules/lodash/identity.js": {
    "bundled": 414,
    "minified": 93,
    "gzipped": 91
  },
  "_virtual/identity.js_commonjs-proxy": {
    "bundled": 106,
    "minified": 96,
    "gzipped": 97
  },
  "node_modules/lodash/_isFlattenable.js": {
    "bundled": 672,
    "minified": 349,
    "gzipped": 196
  },
  "_virtual/_isFlattenable.js_commonjs-proxy": {
    "bundled": 124,
    "minified": 114,
    "gzipped": 102
  },
  "node_modules/lodash/_setCacheAdd.js": {
    "bundled": 472,
    "minified": 189,
    "gzipped": 154
  },
  "_virtual/_setCacheAdd.js_commonjs-proxy": {
    "bundled": 118,
    "minified": 108,
    "gzipped": 102
  },
  "node_modules/lodash/_setCacheHas.js": {
    "bundled": 364,
    "minified": 122,
    "gzipped": 109
  },
  "_virtual/_setCacheHas.js_commonjs-proxy": {
    "bundled": 118,
    "minified": 108,
    "gzipped": 102
  },
  "node_modules/lodash/_assocIndexOf.js": {
    "bundled": 540,
    "minified": 185,
    "gzipped": 153
  },
  "_virtual/_assocIndexOf.js_commonjs-proxy": {
    "bundled": 121,
    "minified": 111,
    "gzipped": 104
  },
  "_virtual/_mapCacheDelete.js_commonjs-proxy": {
    "bundled": 127,
    "minified": 117,
    "gzipped": 103
  },
  "node_modules/lodash/_mapCacheDelete.js": {
    "bundled": 509,
    "minified": 212,
    "gzipped": 155
  },
  "node_modules/lodash/_mapCacheClear.js": {
    "bundled": 461,
    "minified": 283,
    "gzipped": 180
  },
  "_virtual/_mapCacheClear.js_commonjs-proxy": {
    "bundled": 124,
    "minified": 114,
    "gzipped": 102
  },
  "node_modules/lodash/_mapCacheGet.js": {
    "bundled": 383,
    "minified": 172,
    "gzipped": 135
  },
  "_virtual/_mapCacheGet.js_commonjs-proxy": {
    "bundled": 118,
    "minified": 108,
    "gzipped": 103
  },
  "_virtual/_mapCacheSet.js_commonjs-proxy": {
    "bundled": 118,
    "minified": 108,
    "gzipped": 103
  },
  "node_modules/lodash/_mapCacheSet.js": {
    "bundled": 542,
    "minified": 223,
    "gzipped": 163
  },
  "node_modules/lodash/_mapCacheHas.js": {
    "bundled": 435,
    "minified": 172,
    "gzipped": 135
  },
  "_virtual/_mapCacheHas.js_commonjs-proxy": {
    "bundled": 118,
    "minified": 108,
    "gzipped": 102
  },
  "_virtual/_baseIsNative.js_commonjs-proxy": {
    "bundled": 121,
    "minified": 111,
    "gzipped": 104
  },
  "node_modules/lodash/_baseIsNative.js": {
    "bundled": 1483,
    "minified": 716,
    "gzipped": 375
  },
  "node_modules/lodash/_getValue.js": {
    "bundled": 367,
    "minified": 111,
    "gzipped": 109
  },
  "_virtual/_getValue.js_commonjs-proxy": {
    "bundled": 109,
    "minified": 99,
    "gzipped": 99
  },
  "node_modules/lodash/_baseIsArguments.js": {
    "bundled": 552,
    "minified": 273,
    "gzipped": 170
  },
  "_virtual/_baseIsArguments.js_commonjs-proxy": {
    "bundled": 130,
    "minified": 120,
    "gzipped": 106
  },
  "_virtual/_getMapData.js_commonjs-proxy": {
    "bundled": 115,
    "minified": 105,
    "gzipped": 102
  },
  "node_modules/lodash/_getMapData.js": {
    "bundled": 451,
    "minified": 216,
    "gzipped": 167
  },
  "node_modules/lodash/_Hash.js": {
    "bundled": 806,
    "minified": 487,
    "gzipped": 250
  },
  "_virtual/_Hash.js_commonjs-proxy": {
    "bundled": 97,
    "minified": 87,
    "gzipped": 95
  },
  "node_modules/lodash/_isMasked.js": {
    "bundled": 613,
    "minified": 300,
    "gzipped": 215
  },
  "_virtual/_isMasked.js_commonjs-proxy": {
    "bundled": 109,
    "minified": 99,
    "gzipped": 99
  },
  "node_modules/lodash/_isKeyable.js": {
    "bundled": 474,
    "minified": 184,
    "gzipped": 148
  },
  "_virtual/_isKeyable.js_commonjs-proxy": {
    "bundled": 112,
    "minified": 102,
    "gzipped": 100
  },
  "node_modules/lodash/_coreJsData.js": {
    "bundled": 208,
    "minified": 134,
    "gzipped": 115
  },
  "_virtual/_coreJsData.js_commonjs-proxy": {
    "bundled": 115,
    "minified": 105,
    "gzipped": 101
  },
  "node_modules/lodash/_hashClear.js": {
    "bundled": 331,
    "minified": 196,
    "gzipped": 146
  },
  "_virtual/_hashClear.js_commonjs-proxy": {
    "bundled": 112,
    "minified": 102,
    "gzipped": 99
  },
  "node_modules/lodash/_hashGet.js": {
    "bundled": 817,
    "minified": 368,
    "gzipped": 246
  },
  "_virtual/_hashGet.js_commonjs-proxy": {
    "bundled": 106,
    "minified": 96,
    "gzipped": 98
  },
  "node_modules/lodash/_hashDelete.js": {
    "bundled": 491,
    "minified": 159,
    "gzipped": 137
  },
  "_virtual/_hashDelete.js_commonjs-proxy": {
    "bundled": 115,
    "minified": 105,
    "gzipped": 100
  },
  "node_modules/lodash/_hashHas.js": {
    "bundled": 671,
    "minified": 277,
    "gzipped": 193
  },
  "_virtual/_hashHas.js_commonjs-proxy": {
    "bundled": 106,
    "minified": 96,
    "gzipped": 98
  },
  "node_modules/lodash/_hashSet.js": {
    "bundled": 643,
    "minified": 278,
    "gzipped": 209
  },
  "_virtual/_hashSet.js_commonjs-proxy": {
    "bundled": 106,
    "minified": 96,
    "gzipped": 98
  },
  "node_modules/lodash/_nativeCreate.js": {
    "bundled": 242,
    "minified": 152,
    "gzipped": 115
  },
  "_virtual/_nativeCreate.js_commonjs-proxy": {
    "bundled": 121,
    "minified": 111,
    "gzipped": 101
  },
  "node_modules/zxcvbn/lib/frequency_lists.js": {
    "bundled": 793054,
    "minified": 792958,
    "gzipped": 387683
  },
  "genjo-ui.production.min.js": {
    "bundled": 1734297,
    "minified": 1132672,
    "gzipped": 491216
  }
}
